i21y/__init__.py
i21y/abc.py
i21y/error.py
i21y/py.typed
i21y/translator.py
i21y/utils.py
i21y/loaders/__init__.py
i21y/loaders/file_.py
i21y/loaders/json.py
i21y/loaders/yaml.py
i21y-0.4.1.dist-info/METADATA
i21y-0.4.1.dist-info/WHEEL
i21y-0.4.1.dist-info/licenses/LICENSE
i21y-0.4.1.dist-info/RECORD
