Metadata-Version: 2.4
Name: i21y
Version: 0.4.1
Summary: The simple library for i18n support.
Project-URL: Source, https://github.com/tasuren/i21y
Project-URL: Documentation, https://i21y.readthedocs.io/
Author-email: Takagi Tasuku <tasuren@outlook.jp>
License-Expression: MIT
License-File: LICENSE
Keywords: i18n
Classifier: Programming Language :: Python :: 3.11
Classifier: Programming Language :: Python :: 3.12
Classifier: Programming Language :: Python :: 3.13
Classifier: Programming Language :: Python :: 3.14
Classifier: Topic :: Software Development :: Internationalization
Classifier: Typing :: Typed
Requires-Python: >=3.11
Provides-Extra: fast-json
Requires-Dist: orjson~=3.11.6; extra == 'fast-json'
Provides-Extra: yaml
Requires-Dist: pyyaml~=6.0; extra == 'yaml'
